dotenv/__init__.py
dotenv/__main__.py
dotenv/cli.py
dotenv/crypt.py
dotenv/ipython.py
dotenv/main.py
dotenv/parser.py
dotenv/py.typed
dotenv/variables.py
dotenv/version.py
royman_dotenv-1.1.2.dist-info/LICENSE
royman_dotenv-1.1.2.dist-info/METADATA
royman_dotenv-1.1.2.dist-info/WHEEL
royman_dotenv-1.1.2.dist-info/entry_points.txt
royman_dotenv-1.1.2.dist-info/top_level.txt
royman_dotenv-1.1.2.dist-info/RECORD
